pytest_testrail/__init__.py
pytest_testrail/conftest.py
pytest_testrail/plugin.py
pytest_testrail/testrail_api.py
fd_test_rail-1.0.0.dist-info/LICENSE
fd_test_rail-1.0.0.dist-info/METADATA
fd_test_rail-1.0.0.dist-info/WHEEL
fd_test_rail-1.0.0.dist-info/entry_points.txt
fd_test_rail-1.0.0.dist-info/top_level.txt
fd_test_rail-1.0.0.dist-info/RECORD
