Metadata-Version: 2.1
Name: fd-test-rail
Version: 1.0.0
Summary: pytest plugin for creating TestRail runs and adding results self
Home-page: UNKNOWN
Author: UNKNOWN
Author-email: UNKNOWN
License: UNKNOWN
Platform: UNKNOWN
Requires-Dist: pytest (>=3.6)
Requires-Dist: requests (>=2.20.0)
